odoo/addons/l10n_ro_stock_account_date_wizard/README.rst
odoo/addons/l10n_ro_stock_account_date_wizard/__init__.py
odoo/addons/l10n_ro_stock_account_date_wizard/__manifest__.py
odoo/addons/l10n_ro_stock_account_date_wizard/i18n/l10n_ro_stock_account_date_wizard.pot
odoo/addons/l10n_ro_stock_account_date_wizard/i18n/ro.po
odoo/addons/l10n_ro_stock_account_date_wizard/readme/CONTRIBUTORS.md
odoo/addons/l10n_ro_stock_account_date_wizard/readme/DESCRIPTION.md
odoo/addons/l10n_ro_stock_account_date_wizard/readme/INSTALL.md
odoo/addons/l10n_ro_stock_account_date_wizard/static/description/icon.png
odoo/addons/l10n_ro_stock_account_date_wizard/static/description/index.html
odoo/addons/l10n_ro_stock_account_date_wizard/tests/__init__.py
odoo/addons/l10n_ro_stock_account_date_wizard/tests/test_stock_accounting_date.py
odoo/addons/l10n_ro_stock_account_date_wizard/wizard/__init__.py
odoo/addons/l10n_ro_stock_account_date_wizard/wizard/stock_backorder_confirmation.py
odoo/addons/l10n_ro_stock_account_date_wizard/wizard/stock_backorder_confirmation_views.xml
odoo_addon_l10n_ro_stock_account_date_wizard-19.0.1.1.0.dist-info/METADATA
odoo_addon_l10n_ro_stock_account_date_wizard-19.0.1.1.0.dist-info/WHEEL
odoo_addon_l10n_ro_stock_account_date_wizard-19.0.1.1.0.dist-info/top_level.txt
odoo_addon_l10n_ro_stock_account_date_wizard-19.0.1.1.0.dist-info/RECORD
